fiat/__init__.py
fiat/apps/__init__.py
fiat/apps/computing.py
fiat/apps/dashboard.py
fiat/apps/devs.py
fiat/apps/envd.py
fiat/apps/job.py
fiat/apps/juicefs.py
fiat/apps/metastore.py
fiat/apps/server.py
fiat/apps/templates.py
fiat/apps/utils.py
fiat/main.py
fiat_cli-0.7.0.dist-info/entry_points.txt
fiat_cli-0.7.0.dist-info/LICENSE
fiat_cli-0.7.0.dist-info/WHEEL
fiat_cli-0.7.0.dist-info/METADATA
fiat_cli-0.7.0.dist-info/RECORD
