Metadata-Version: 2.1
Name: fiat-cli
Version: 0.7.0
Summary: 🤩 - Fiat CLI Component
License: MIT
Author: Jiacheng Li
Author-email: cheng2029@foxmail.com
Requires-Python: >=3.10,<4.0
Classifier: License :: OSI Approved :: MIT License
Classifier: Programming Language :: Python :: 3
Classifier: Programming Language :: Python :: 3.10
Classifier: Programming Language :: Python :: 3.11
Requires-Dist: docker (>=6.0.1,<7.0.0)
Requires-Dist: envd (>=0.3.21,<0.4.0)
Requires-Dist: ray[default] (>=2.4.0,<3.0.0)
Requires-Dist: typer[all] (>=0.7.0,<0.8.0)
